material_caculation/__init__.py
material_caculation/main.py
material_caculation-1.0.2.dist-info/METADATA
material_caculation-1.0.2.dist-info/WHEEL
material_caculation-1.0.2.dist-info/top_level.txt
material_caculation-1.0.2.dist-info/RECORD
